pyxunlei/__init__.py
pyxunlei/pyxunlei.py
pyxunlei_for_nastool-0.1.0.dist-info/LICENSE
pyxunlei_for_nastool-0.1.0.dist-info/METADATA
pyxunlei_for_nastool-0.1.0.dist-info/WHEEL
pyxunlei_for_nastool-0.1.0.dist-info/RECORD
