Metadata-Version: 2.1
Name: pyxunlei-for-nastool
Version: 0.1.0
Summary: 基于Docker版本的迅雷API客户端，可作为NAStool的下载器插件使用
Home-page: https://github.com/Dominique9898/pyxunlei-for-nastool
Keywords: xunlei,download,docker,nastool,nas
Author: dominikwei
Author-email: dominikwei9988@outlook.com
Requires-Python: >=3.10,<4.0
Classifier: Development Status :: 4 - Beta
Classifier: Intended Audience :: Developers
Classifier: Operating System :: OS Independent
Classifier: Programming Language :: Python :: 3
Classifier: Programming Language :: Python :: 3.10
Classifier: Programming Language :: Python :: 3.11
Classifier: Programming Language :: Python :: 3.12
Classifier: Programming Language :: Python :: 3.13
Requires-Dist: charset-normalizer (>=3.0.0,<4.0.0)
Requires-Dist: loguru (>=0.7.2,<0.8.0)
Requires-Dist: pydantic (>=2.6.0,<3.0.0)
Requires-Dist: python-dateutil (>=2.8.2,<3.0.0)
Requires-Dist: requests (>=2.31.0,<3.0.0)
Requires-Dist: torrentool (>=1.2.0,<2.0.0)
Requires-Dist: typing-extensions (>=4.0.0,<5.0.0)
Requires-Dist: urllib3 (>=2.0.0,<3.0.0)
Project-URL: Repository, https://github.com/Dominique9898/pyxunlei-for-nastool
